whatsapp_mcp/__init__.py
whatsapp_mcp/main.py
whatsapp_mcp/models.py
whatsapp_mcp/server.py
whatsapp_mcp/modules/__init__.py
whatsapp_mcp/modules/auth.py
whatsapp_mcp/modules/group.py
whatsapp_mcp/modules/message.py
whatsapp_mcp_server-0.2.1.dist-info/licenses/LICENSE
whatsapp_mcp_server-0.2.1.dist-info/METADATA
whatsapp_mcp_server-0.2.1.dist-info/WHEEL
whatsapp_mcp_server-0.2.1.dist-info/entry_points.txt
whatsapp_mcp_server-0.2.1.dist-info/top_level.txt
whatsapp_mcp_server-0.2.1.dist-info/RECORD
