Metadata-Version: 2.4
Name: whatsapp-mcp-server
Version: 0.2.1
Summary: A MCP server that provides an API to interact with WhatsApp
Author-email: Manuel Saelices <msaelices@gmail.com>
License: MIT License
Project-URL: Homepage, https://github.com/msaelices/whatsapp-mcp-server
Classifier: Programming Language :: Python :: 3
Classifier: Programming Language :: Python :: 3.10
Classifier: License :: OSI Approved :: MIT License
Classifier: Operating System :: OS Independent
Requires-Python: >=3.10
License-File: LICENSE
Requires-Dist: pydantic>=2.0.0
Requires-Dist: Pillow>=9.0.0
Requires-Dist: click>=8.0.0
Requires-Dist: mcp>=1.6.0
Requires-Dist: whatsapp-api-client-python==0.0.49
Requires-Dist: python-dotenv>=1.0.0
Provides-Extra: dev
Requires-Dist: pytest>=7.0.0; extra == "dev"
Requires-Dist: pytest-asyncio>=0.25.3; extra == "dev"
Requires-Dist: mypy>=1.0.0; extra == "dev"
Requires-Dist: flake8>=6.0.0; extra == "dev"
Requires-Dist: isort>=5.0.0; extra == "dev"
Requires-Dist: black>=23.0.0; extra == "dev"
Dynamic: license-file
